langchain_moonshot/__init__.py
langchain_moonshot/chat_models/__init__.py
langchain_moonshot/chat_models/azure.py
langchain_moonshot/chat_models/base.py
langchain_moonshot/embeddings/__init__.py
langchain_moonshot/embeddings/azure.py
langchain_moonshot/embeddings/base.py
langchain_moonshot/llms/__init__.py
langchain_moonshot/llms/azure.py
langchain_moonshot/llms/base.py
langchain_moonshot/output_parsers/__init__.py
langchain_moonshot/output_parsers/tools.py
langchain_moonshot/py.typed
langchain_moonshot-0.0.7.dist-info/LICENSE
langchain_moonshot-0.0.7.dist-info/METADATA
langchain_moonshot-0.0.7.dist-info/WHEEL
langchain_moonshot-0.0.7.dist-info/RECORD
