Metadata-Version: 2.1
Name: langchain-moonshot
Version: 0.0.7
Summary: An integration package connecting Moonshot AI and LangChain
Home-page: https://github.com/RyanFeiluX/langchain_moonshot
License: MIT
Author: Ryan Xiao
Requires-Python: >=3.8.1,<4.0
Classifier: License :: OSI Approved :: MIT License
Classifier: Programming Language :: Python :: 3
Classifier: Programming Language :: Python :: 3.9
Classifier: Programming Language :: Python :: 3.10
Classifier: Programming Language :: Python :: 3.11
Classifier: Programming Language :: Python :: 3.12
Requires-Dist: langchain (>=1.1.13,<2.0.0)
Requires-Dist: langchain-core (>=0.1.33,<0.2.0)
Requires-Dist: openai (>=1.10.0,<2.0.0)
Requires-Dist: tiktoken (>=0.5.2,<1)
Project-URL: Repository, https://github.com/RyanFeiluX/langchain_moonshot
Project-URL: Source Code, https://github.com/langchain-ai/langchain/tree/master/libs/partners/openai
